polyno/__init__.py
polyno-1.2.5.dist-info/LICENSE
polyno-1.2.5.dist-info/METADATA
polyno-1.2.5.dist-info/WHEEL
polyno-1.2.5.dist-info/top_level.txt
polyno-1.2.5.dist-info/RECORD
