Metadata-Version: 2.1
Name: polyno
Version: 1.2.5
Summary: Polyno: polynomial object
Home-page: https://github.com/Ridoineel/Polyno
Author: RidoineEl
Author-email: ridoineelofficiel@gmail.com
Project-URL: Bug Tracker, https://github.com/Ridoineel/Polyno/issues
Classifier: Programming Language :: Python :: 3
Classifier: License :: OSI Approved :: MIT License
Classifier: Operating System :: OS Independent
Requires-Python: >=3.6
License-File: LICENSE
